src/BlueBook.csv
src/__init__.py
src/visitsite.py
bluebook_cite_abbreviation_fixer-0.0.1.dist-info/METADATA
bluebook_cite_abbreviation_fixer-0.0.1.dist-info/WHEEL
bluebook_cite_abbreviation_fixer-0.0.1.dist-info/licenses/LICENCE
bluebook_cite_abbreviation_fixer-0.0.1.dist-info/RECORD
