Metadata-Version: 2.3
Name: BlueBook_Cite_Abbreviation_Fixer
Version: 0.0.1
Summary: The JohnnyTech BlueBook Cite Abbreviation Fixer, as a Python package.
Project-URL: Homepage, https://bluebook.johnnytech.net
Author-email: Johnny Konczal <johnny@johnnytech.net>
License-File: LICENCE
Classifier: Operating System :: OS Independent
Classifier: Programming Language :: Python :: 3
Requires-Python: >=3.12
